pyresource/status.py
pyresource/_compat.py
pyresource/form.py
pyresource/auth.py
pyresource/utils.py
pyresource/response.py
pyresource/filter.py
pyresource/__init__.py
pyresource/resource.py
pyresource/exceptions.py
pyresource/view.py
pyresource/serializer.py
pyresource/conf/__init__.py
pyresource/conf/default_settings.py
pyresource/contrib/dufilter.py
pyresource/contrib/root.py
pyresource/contrib/__init__.py
pyresource/contrib/db/__init__.py
pyresource/contrib/db/shared_schema.py
pyresource/contrib/db/mongo/__init__.py
pyresource/contrib/db/mongo/view.py
pyresource/contrib/db/mongo/serializer.py
pyresource/contrib/db/sqla/__init__.py
pyresource/contrib/db/sqla/view.py
pyresource/contrib/db/sqla/serializer.py
pyresource/contrib/token/user.py
pyresource/contrib/token/auth.py
pyresource/contrib/token/signer.py
pyresource/contrib/token/__init__.py
pyresource/contrib/token/view.py
pyresource/framework/flask.py
pyresource/framework/django.py
pyresource/framework/__init__.py
pyresource/framework/view.py
Resource-0.2.0.dist-info/metadata.json
Resource-0.2.0.dist-info/RECORD
Resource-0.2.0.dist-info/METADATA
Resource-0.2.0.dist-info/DESCRIPTION.rst
Resource-0.2.0.dist-info/WHEEL
Resource-0.2.0.dist-info/top_level.txt
rsrc/status.py
rsrc/_compat.py
rsrc/form.py
rsrc/auth.py
rsrc/utils.py
rsrc/response.py
rsrc/filter.py
rsrc/__init__.py
rsrc/resource.py
rsrc/exceptions.py
rsrc/view.py
rsrc/serializer.py
rsrc/request.py
rsrc/logger.py
rsrc/conf/__init__.py
rsrc/conf/default_settings.py
rsrc/contrib/dufilter.py
rsrc/contrib/root.py
rsrc/contrib/__init__.py
rsrc/contrib/db/__init__.py
rsrc/contrib/db/shared_schema.py
rsrc/contrib/db/mongo/__init__.py
rsrc/contrib/db/mongo/view.py
rsrc/contrib/db/mongo/serializer.py
rsrc/contrib/db/sqla/__init__.py
rsrc/contrib/db/sqla/view.py
rsrc/contrib/db/sqla/serializer.py
rsrc/contrib/token/user.py
rsrc/contrib/token/auth.py
rsrc/contrib/token/signer.py
rsrc/contrib/token/__init__.py
rsrc/contrib/token/view.py
rsrc/framework/flask.py
rsrc/framework/django.py
rsrc/framework/__init__.py
rsrc/framework/view.py
